hatch_nativelib/__init__.py
hatch_nativelib/_version.py
hatch_nativelib/config.py
hatch_nativelib/hooks.py
hatch_nativelib/plugin.py
hatch_nativelib/util.py
hatch_nativelib/validate.py
hatch_nativelib-0.2.0.dist-info/METADATA
hatch_nativelib-0.2.0.dist-info/WHEEL
hatch_nativelib-0.2.0.dist-info/entry_points.txt
hatch_nativelib-0.2.0.dist-info/RECORD
