Metadata-Version: 2.4
Name: hatch-nativelib
Version: 0.2.0
Summary: Hatchling plugin with utilities for native libraries
Project-URL: Source code, https://github.com/robotpy/hatch-nativelib
Author-email: Dustin Spicuzza <dustin@virtualroadside.com>
License-Expression: BSD-3-Clause
Keywords: hatch,pkgconf
Classifier: Framework :: Hatch
Requires-Python: >=3.8
Requires-Dist: hatchling
Requires-Dist: packaging
Requires-Dist: pkgconf
Requires-Dist: validobj~=1.2
